turbtools/__init__.py
turbtools/plot_stationarity.py
turbtools/plotsignal.py
turbtools/turbtools.py
turbtools-22.8a2.dist-info/METADATA
turbtools-22.8a2.dist-info/WHEEL
turbtools-22.8a2.dist-info/entry_points.txt
turbtools-22.8a2.dist-info/top_level.txt
turbtools-22.8a2.dist-info/RECORD
