Metadata-Version: 2.1
Name: turbtools
Version: 22.8a2
Summary: Python Package for Statistical Analysis of Turbulence Data
Home-page: https://github.com/aakash30jan/turbtools
Author: Lille Turbulence Program 2022
Maintainer: Aakash Patil
License: GPL
Keywords: turbulence fluids analysis stats
Platform: any
Classifier: Programming Language :: Python :: 3
Classifier: License :: OSI Approved :: GNU General Public License v3 (GPLv3)
Classifier: Operating System :: OS Independent
Requires-Dist: h5py
Requires-Dist: matplotlib
Requires-Dist: numpy
Requires-Dist: requests
Requires-Dist: scipy
